jupyterlab_box_drive/.eslintignore
jupyterlab_box_drive/.eslintrc.js
jupyterlab_box_drive/.gitignore
jupyterlab_box_drive/.prettierignore
jupyterlab_box_drive/.prettierrc
jupyterlab_box_drive/.stylelintrc
jupyterlab_box_drive/__init__.py
jupyterlab_box_drive/_version.py
jupyterlab_box_drive/labextension/package.json
jupyterlab_box_drive/labextension/static/611.8052357e177db1275b51.js
jupyterlab_box_drive/labextension/static/747.75e36de11fd8b24a39c9.js
jupyterlab_box_drive/labextension/static/remoteEntry.9f7e621c97b7d7b19354.js
jupyterlab_box_drive/labextension/static/style.js
jupyterlab_box_drive/labextension/static/third-party-licenses.json
jupyterlab_box_drive/labextension/static/assets/BoxSdk.min.js
jupyterlab_box_drive/labextension/static/assets/auth.html
jupyterlab_box_drive-0.2.0.data/data/share/jupyter/labextensions/jupyterlab-box-drive/package.json
jupyterlab_box_drive-0.2.0.data/data/share/jupyter/labextensions/jupyterlab-box-drive/static/611.8052357e177db1275b51.js
jupyterlab_box_drive-0.2.0.data/data/share/jupyter/labextensions/jupyterlab-box-drive/static/747.75e36de11fd8b24a39c9.js
jupyterlab_box_drive-0.2.0.data/data/share/jupyter/labextensions/jupyterlab-box-drive/static/remoteEntry.9f7e621c97b7d7b19354.js
jupyterlab_box_drive-0.2.0.data/data/share/jupyter/labextensions/jupyterlab-box-drive/static/style.js
jupyterlab_box_drive-0.2.0.data/data/share/jupyter/labextensions/jupyterlab-box-drive/static/third-party-licenses.json
jupyterlab_box_drive-0.2.0.data/data/share/jupyter/labextensions/jupyterlab-box-drive/static/assets/BoxSdk.min.js
jupyterlab_box_drive-0.2.0.data/data/share/jupyter/labextensions/jupyterlab-box-drive/static/assets/auth.html
jupyterlab_box_drive-0.2.0.data/data/share/jupyter/labextensions/jupyterlab-box-drive/install.json
jupyterlab_box_drive-0.2.0.dist-info/METADATA
jupyterlab_box_drive-0.2.0.dist-info/WHEEL
jupyterlab_box_drive-0.2.0.dist-info/licenses/LICENSE
jupyterlab_box_drive-0.2.0.dist-info/licenses/LICENSE-box-javascript-sdk
jupyterlab_box_drive-0.2.0.dist-info/RECORD
