Metadata-Version: 2.1
Name: jupyterlab_box_drive
Version: 0.2.0
Summary: A JupyterLab extension that provides direct access to Box cloud storage.
Project-URL: Homepage, https://github.com/tanaga9/jupyterlab-box-drive
Project-URL: Bug Tracker, https://github.com/tanaga9/jupyterlab-box-drive/issues
Project-URL: Repository, https://github.com/tanaga9/jupyterlab-box-drive.git
Author-email: tanaga9 <tanaga9@users.noreply.github.com>
License: BSD 3-Clause License
License-File: LICENSE
License-File: LICENSE-box-javascript-sdk
Classifier: Framework :: Jupyter
Classifier: Framework :: Jupyter :: JupyterLab
Classifier: Framework :: Jupyter :: JupyterLab :: 3
Classifier: Framework :: Jupyter :: JupyterLab :: Extensions
Classifier: Framework :: Jupyter :: JupyterLab :: Extensions :: Prebuilt
Classifier: License :: OSI Approved :: BSD License
Classifier: Programming Language :: Python
Classifier: Programming Language :: Python :: 3
Classifier: Programming Language :: Python :: 3.7
Classifier: Programming Language :: Python :: 3.8
Classifier: Programming Language :: Python :: 3.9
Classifier: Programming Language :: Python :: 3.10
Classifier: Programming Language :: Python :: 3.11
Requires-Python: >=3.7
